pretix_cartshare/__init__.py
pretix_cartshare/forms.py
pretix_cartshare/models.py
pretix_cartshare/signals.py
pretix_cartshare/urls.py
pretix_cartshare/views.py
pretix_cartshare/locale/django.pot
pretix_cartshare/locale/ar/LC_MESSAGES/django.mo
pretix_cartshare/locale/ar/LC_MESSAGES/django.po
pretix_cartshare/locale/cs/LC_MESSAGES/django.mo
pretix_cartshare/locale/cs/LC_MESSAGES/django.po
pretix_cartshare/locale/da/LC_MESSAGES/django.mo
pretix_cartshare/locale/da/LC_MESSAGES/django.po
pretix_cartshare/locale/de/LC_MESSAGES/django.mo
pretix_cartshare/locale/de/LC_MESSAGES/django.po
pretix_cartshare/locale/de_Informal/LC_MESSAGES/django.mo
pretix_cartshare/locale/de_Informal/LC_MESSAGES/django.po
pretix_cartshare/locale/es/LC_MESSAGES/django.mo
pretix_cartshare/locale/es/LC_MESSAGES/django.po
pretix_cartshare/locale/fr/LC_MESSAGES/django.mo
pretix_cartshare/locale/fr/LC_MESSAGES/django.po
pretix_cartshare/locale/it/LC_MESSAGES/django.mo
pretix_cartshare/locale/it/LC_MESSAGES/django.po
pretix_cartshare/locale/nl/LC_MESSAGES/django.mo
pretix_cartshare/locale/nl/LC_MESSAGES/django.po
pretix_cartshare/locale/nl_BE/LC_MESSAGES/django.mo
pretix_cartshare/locale/nl_BE/LC_MESSAGES/django.po
pretix_cartshare/locale/pt_BR/LC_MESSAGES/django.mo
pretix_cartshare/locale/pt_BR/LC_MESSAGES/django.po
pretix_cartshare/locale/tr/LC_MESSAGES/django.mo
pretix_cartshare/locale/tr/LC_MESSAGES/django.po
pretix_cartshare/migrations/0001_initial.py
pretix_cartshare/migrations/0002_auto_20161008_1047.py
pretix_cartshare/migrations/__init__.py
pretix_cartshare/templates/pretixplugins/cartshare/create.html
pretix_cartshare/templates/pretixplugins/cartshare/delete.html
pretix_cartshare/templates/pretixplugins/cartshare/list.html
pretix_cartshare/templates/pretixplugins/cartshare/redeem.html
pretix_cartshare-1.6.dist-info/LICENSE
pretix_cartshare-1.6.dist-info/METADATA
pretix_cartshare-1.6.dist-info/WHEEL
pretix_cartshare-1.6.dist-info/entry_points.txt
pretix_cartshare-1.6.dist-info/top_level.txt
pretix_cartshare-1.6.dist-info/RECORD
