Metadata-Version: 2.1
Name: pretix-cartshare
Version: 1.6
Summary: pretix plugin to share carts
Home-page: https://pretix.eu
Author: Raphael Michel
Author-email: mail@raphaelmichel.de
License: UNKNOWN
Platform: UNKNOWN
